applaunchservices/__init__.py
applaunchservices/_dummy.py
applaunchservices/_ls.py
applaunchservices-0.3.0.dist-info/LICENSE.txt
applaunchservices-0.3.0.dist-info/METADATA
applaunchservices-0.3.0.dist-info/WHEEL
applaunchservices-0.3.0.dist-info/top_level.txt
applaunchservices-0.3.0.dist-info/RECORD
