Metadata-Version: 2.1
Name: applaunchservices
Version: 0.3.0
Summary: Simple package for registering an app with apple Launch Services to handle UTI and URL
Home-page: https://github.com/impact27/applaunchservices
Author: Quentin Peter
Author-email: qpeter@bluewin.ch
Classifier: Programming Language :: Python :: 3
Classifier: Programming Language :: Python :: 2
Classifier: License :: OSI Approved :: MIT License
Classifier: Operating System :: MacOS
License-File: LICENSE.txt
